testcatplzignore/__init__.py
testcatplzignore-0.0.1.dist-info/METADATA
testcatplzignore-0.0.1.dist-info/WHEEL
testcatplzignore-0.0.1.dist-info/top_level.txt
testcatplzignore-0.0.1.dist-info/RECORD
