Metadata-Version: 2.1
Name: testcatplzignore
Version: 0.0.1
Summary: Internal utility package
Requires-Python: >=3.6
